sthali_db/__init__.py
sthali_db/db.py
sthali_db/dependencies.py
sthali_db/models.py
sthali_db/types.py
sthali_db/clients/__init__.py
sthali_db/clients/default.py
sthali_db/clients/postgres.py
sthali_db/clients/redis.py
sthali_db/clients/sqlite.py
sthali_db/clients/tinydb.py
sthali_db-0.0.3.dist-info/licenses/LICENSE
sthali_db-0.0.3.dist-info/METADATA
sthali_db-0.0.3.dist-info/WHEEL
sthali_db-0.0.3.dist-info/top_level.txt
sthali_db-0.0.3.dist-info/RECORD
