Metadata-Version: 2.4
Name: sthali-db
Version: 0.0.3
Summary: A FastAPI package dependency for SthaliCRUD perform DB queries
Author-email: Jhunu Fernandes <jhunu.fernandes@gmail.com>
Project-URL: Homepage, https://github.com/project-sthali/sthali-db
Project-URL: Bug Tracker, https://github.com/project-sthali/sthali-db/issues
Project-URL: Source, https://github.com/project-sthali/sthali-db
Project-URL: Documentation, https://project-sthali.github.io/sthali-db
Project-URL: Changelog, https://github.com/project-sthali/sthali-db/releases
Classifier: License :: OSI Approved :: MIT License
Classifier: Operating System :: OS Independent
Classifier: Programming Language :: Python :: 3.10
Classifier: Programming Language :: Python :: 3.11
Classifier: Programming Language :: Python :: 3.12
Classifier: Programming Language :: Python :: 3.13
Classifier: Topic :: Internet :: WWW/HTTP :: HTTP Servers
Classifier: Topic :: Internet :: WWW/HTTP
Classifier: Topic :: Internet
Classifier: Topic :: Software Development :: Libraries :: Application Frameworks
Classifier: Topic :: Software Development :: Libraries :: Python Modules
Classifier: Topic :: Software Development :: Libraries
Classifier: Topic :: Software Development
Classifier: Typing :: Typed
Requires-Python: >=3.10
License-File: LICENSE
Requires-Dist: sthali-core>=0.0.11
Requires-Dist: tinydb>=4.8.2
Provides-Extra: dev
Requires-Dist: coverage[toml]>=7.9.1; extra == "dev"
Requires-Dist: ruff>=0.12.0; extra == "dev"
Provides-Extra: tests
Requires-Dist: coverage[toml]>=7.9.1; extra == "tests"
Provides-Extra: stage
Requires-Dist: build>=1.2.1; extra == "stage"
Requires-Dist: coverage[toml]>=7.9.1; extra == "stage"
Dynamic: license-file
